embedding_as_service_client/__init__.py
embedding_as_service_client-1.0.0.dist-info/METADATA
embedding_as_service_client-1.0.0.dist-info/WHEEL
embedding_as_service_client-1.0.0.dist-info/top_level.txt
embedding_as_service_client-1.0.0.dist-info/RECORD
