Metadata-Version: 2.1
Name: embedding-as-service-client
Version: 1.0.0
Summary: embedding-as-service: one-stop solution to encode sentence to vectors using various embedding methods
Home-page: https://github.com/amansrivastava17/embedding-as-service
Author: Aman Srivastava
Author-email: amans.rlx@gmail.com
License: UNKNOWN
Keywords: bert nlp tensorflow machine learning sentence encoding embedding serving albert glove word2vec
Platform: UNKNOWN
Classifier: Programming Language :: Python :: 3.6
Classifier: License :: OSI Approved :: MIT License
Classifier: Operating System :: OS Independent
Requires-Python: >=3.6
Requires-Dist: requests (==2.21.0)
Requires-Dist: setuptools (>=41.0.0)
